Data42/Cleaning.py
Data42/Functions.py
Data42/Learning.py
Data42/Visualization.py
Data42/__init__.py
Data42-0.0.9.dist-info/METADATA
Data42-0.0.9.dist-info/WHEEL
Data42-0.0.9.dist-info/top_level.txt
Data42-0.0.9.dist-info/RECORD
