Metadata-Version: 2.1
Name: Data42
Version: 0.0.9
Summary: Library specializing in data cleaning, visualization and prediction
Home-page: https://github.com/pablod1/library-project-TheBridge
Author: Pablo Diaz Gonzalez
Author-email: pablo.diaz.92@outlook.com
License: MIT
Platform: UNKNOWN
Requires-Dist: pandas
Requires-Dist: numpy
Requires-Dist: seaborn
Requires-Dist: matplotlib
Requires-Dist: sklearn
Requires-Dist: scipy
Requires-Dist: imblearn
